matgen/__init__.py
matgen/matast.py
matgen/matgen.py
matgen-0.1.1.dist-info/LICENSE
matgen-0.1.1.dist-info/METADATA
matgen-0.1.1.dist-info/WHEEL
matgen-0.1.1.dist-info/top_level.txt
matgen-0.1.1.dist-info/RECORD
