Metadata-Version: 2.1
Name: matgen
Version: 0.1.1
Summary: Fast matrix generation in python, including python style and matlab style support
Home-page: https://gitee.com/junruoyu-zheng/mat-gen
Author: junruoyu-zheng
Author-email: zhengjry@outlook.com
License: UNKNOWN
Platform: UNKNOWN
Classifier: Programming Language :: Python :: 3
Classifier: License :: OSI Approved :: MIT License
Classifier: Operating System :: OS Independent
Requires-Dist: numpy
